jewcal/__init__.py
jewcal/__main__.py
jewcal/constants.py
jewcal/core.py
jewcal/py.typed
jewcal/helpers/__init__.py
jewcal/helpers/sun.py
jewcal/models/__init__.py
jewcal/models/events.py
jewcal/models/jewish_date.py
jewcal/models/zmanim.py
jewcal/utils/__init__.py
jewcal/utils/calculations.py
jewcal/utils/datetime.py
jewcal-0.8.0.dist-info/LICENSE
jewcal-0.8.0.dist-info/METADATA
jewcal-0.8.0.dist-info/WHEEL
jewcal-0.8.0.dist-info/entry_points.txt
jewcal-0.8.0.dist-info/top_level.txt
jewcal-0.8.0.dist-info/RECORD
