Metadata-Version: 2.1
Name: jewcal
Version: 0.8.0
Summary: Convert Gregorian to Jewish dates with holidays and zmanim (Diaspora/Israel).
Author: essel-dev
License: MIT License
Project-URL: Bug Tracker, https://github.com/essel-dev/jewcal/issues
Project-URL: Changelog, https://github.com/essel-dev/jewcal/releases
Project-URL: Documentation, https://jewcal.readthedocs.io/
Project-URL: GitHub, https://github.com/essel-dev/jewcal
Keywords: jewish calendar,hebrew calendar,zmanim
Classifier: License :: OSI Approved :: MIT License
Classifier: Operating System :: OS Independent
Classifier: Programming Language :: Python :: 3.10
Classifier: Programming Language :: Python :: 3.11
Classifier: Programming Language :: Python :: 3.12
Classifier: Programming Language :: Python :: 3.13
Classifier: Topic :: Utilities
Classifier: Typing :: Typed
Requires-Python: >=3.10
License-File: LICENSE
Requires-Dist: astral>=3.2
Provides-Extra: dev
Requires-Dist: pre-commit; extra == "dev"
Requires-Dist: tox; extra == "dev"
Requires-Dist: sphinx; extra == "dev"
Requires-Dist: sphinx-rtd-theme; extra == "dev"
